kube_hunter/__init__.py
kube_hunter/__main__.py
kube_hunter/conf/__init__.py
kube_hunter/conf/logging.py
kube_hunter/conf/parser.py
kube_hunter/core/__init__.py
kube_hunter/core/events/__init__.py
kube_hunter/core/events/event_handler.py
kube_hunter/core/events/types.py
kube_hunter/core/types/__init__.py
kube_hunter/core/types/components.py
kube_hunter/core/types/hunters.py
kube_hunter/core/types/vulnerabilities.py
kube_hunter/modules/__init__.py
kube_hunter/modules/discovery/__init__.py
kube_hunter/modules/discovery/apiserver.py
kube_hunter/modules/discovery/dashboard.py
kube_hunter/modules/discovery/etcd.py
kube_hunter/modules/discovery/hosts.py
kube_hunter/modules/discovery/kubectl.py
kube_hunter/modules/discovery/kubelet.py
kube_hunter/modules/discovery/kubernetes_client.py
kube_hunter/modules/discovery/ports.py
kube_hunter/modules/discovery/proxy.py
kube_hunter/modules/hunting/__init__.py
kube_hunter/modules/hunting/aks.py
kube_hunter/modules/hunting/apiserver.py
kube_hunter/modules/hunting/capabilities.py
kube_hunter/modules/hunting/certificates.py
kube_hunter/modules/hunting/cves.py
kube_hunter/modules/hunting/dashboard.py
kube_hunter/modules/hunting/etcd.py
kube_hunter/modules/hunting/kubelet.py
kube_hunter/modules/hunting/mounts.py
kube_hunter/modules/hunting/proxy.py
kube_hunter/modules/hunting/secrets.py
kube_hunter/modules/report/__init__.py
kube_hunter/modules/report/base.py
kube_hunter/modules/report/collector.py
kube_hunter/modules/report/dispatchers.py
kube_hunter/modules/report/factory.py
kube_hunter/modules/report/json.py
kube_hunter/modules/report/plain.py
kube_hunter/modules/report/yaml.py
kube_hunter/plugins/__init__.py
kube_hunter/plugins/hookspecs.py
tests/__init__.py
kube_hunter-0.6.8.dist-info/LICENSE
kube_hunter-0.6.8.dist-info/METADATA
kube_hunter-0.6.8.dist-info/WHEEL
kube_hunter-0.6.8.dist-info/entry_points.txt
kube_hunter-0.6.8.dist-info/top_level.txt
kube_hunter-0.6.8.dist-info/RECORD
