Metadata-Version: 2.1
Name: kube-hunter
Version: 0.6.8
Summary: Kubernetes security weaknesses hunter for humans
Home-page: https://github.com/aquasecurity/kube-hunter
Author: Aqua Security
Author-email: support@aquasec.com
License: UNKNOWN
Keywords: aquasec,hunter,kubernetes,k8s,security
Platform: UNKNOWN
Classifier: Development Status :: 4 - Beta
Classifier: Environment :: Console
Classifier: License :: OSI Approved :: Apache Software License
Classifier: Natural Language :: English
Classifier: Operating System :: OS Independent
Classifier: Programming Language :: Python :: 3.6
Classifier: Programming Language :: Python :: 3.7
Classifier: Programming Language :: Python :: 3.8
Classifier: Programming Language :: Python :: 3.9
Classifier: Programming Language :: Python :: 3 :: Only
Classifier: Topic :: Security
Requires-Python: >=3.6
License-File: LICENSE
Requires-Dist: netaddr
Requires-Dist: netifaces
Requires-Dist: requests
Requires-Dist: PrettyTable
Requires-Dist: urllib3 (>=1.24.3)
Requires-Dist: ruamel.yaml
Requires-Dist: future
Requires-Dist: packaging
Requires-Dist: dataclasses
Requires-Dist: pluggy
Requires-Dist: kubernetes (==12.0.1)
